jaine/__init__.py
jaine/main.py
tests/__init__.py
tests/conftest.py
tests/test_main.py
tests/test_version.py
jaine-0.0.1.dist-info/LICENSE
jaine-0.0.1.dist-info/METADATA
jaine-0.0.1.dist-info/WHEEL
jaine-0.0.1.dist-info/top_level.txt
jaine-0.0.1.dist-info/RECORD
